{
    "a": "ae",
    "b": "bee",
    "c": "sieh",
    "d": "dea",
    "e": "ee",
    "f": "F.",
    "g": "jie",
    "h": "edge",
    "i": "eye",
    "j": "jay",
    "k": "kaye",
    "l": "elle",
    "m": "emme",
    "n": "en",
    "o": "owe",
    "p": "pea",
    "q": "queue",
    "r": "are",
    "s": "esse",
    "t": "tea",
    "u": "hugh",
    "v": "vee",
    "w": "doub you",
    "x": "ex",
    "y": "why",
    "z": "zee",
    "1": "one",
    "2": "two",
    "3": "three",
    "4": "four",
    "5": "five",
    "6": "six",
    "7": "seven",
    "8": "eight",
    "9": "nine",
    "0": "zero",
    "&": "and"
}
